ssfp/__init__.py
ssfp/bssfp.py
ssfp/fimtre.py
ssfp/gre.py
ssfp/gs_recon.py
ssfp/planet.py
ssfp/rgphcorr.py
ssfp/robustcc.py
ssfp/utils.py
ssfp/examples/__init__.py
ssfp/examples/basic_bssfp.py
ssfp/examples/basic_fimtre.py
ssfp/examples/basic_gs_recon.py
ssfp/examples/basic_planet.py
ssfp/examples/basic_rgphcorr.py
ssfp/examples/basic_robustcc.py
ssfp/examples/basic_spoiled_gre.py
ssfp/examples/compare_bssfp_gre.py
ssfp/examples/fimtre_illustration.py
ssfp/examples/fimtre_opt.py
ssfp/examples/fimtre_phantom.py
ssfp/examples/fimtre_virt_ellipse.py
ssfp/examples/ormtre_experiments.py
ssfp/examples/robustcc_with_planet.py
ssfp/examples/robustcc_with_planet_knee.py
ssfp-1.2.0.dist-info/LICENSE
ssfp-1.2.0.dist-info/METADATA
ssfp-1.2.0.dist-info/WHEEL
ssfp-1.2.0.dist-info/top_level.txt
ssfp-1.2.0.dist-info/RECORD
