Metadata-Version: 2.1
Name: ssfp
Version: 1.2.0
Summary: SSFP simulation
Author-email: Nicholas McKibben <nicholas.bgp@gmail.com>
Maintainer-email: Nicholas McKibben <nicholas.bgp@gmail.com>
License: Copyright (c) 2023 Nicholas McKibben
Project-URL: Homepage, https://github.com/mckib2/ssfp
Requires-Python: >=3.8
License-File: LICENSE
Requires-Dist: numpy >=1.26.1
Requires-Dist: matplotlib >=3.8.0
Requires-Dist: scikit-image >=0.22.0
Requires-Dist: phantominator >=0.7.0
Requires-Dist: tqdm >=4.66.0
Requires-Dist: ellipsinator >=0.2.1
